zjk_try/__init__.py
zjk_try/zjk_try.py
zjk_try-0.0.1.dist-info/LICENSE
zjk_try-0.0.1.dist-info/METADATA
zjk_try-0.0.1.dist-info/WHEEL
zjk_try-0.0.1.dist-info/top_level.txt
zjk_try-0.0.1.dist-info/RECORD
