Metadata-Version: 2.1
Name: zjk-try
Version: 0.0.1
Summary: I'm zjk! I'm 21! I'm single! Don't wait! Come!
Home-page: https://github.com/junjunjun-learner
Author: junjunjun
Author-email: 996001302@qq.com
License: UNKNOWN
Platform: UNKNOWN
Classifier: Programming Language :: Python :: 3
Classifier: License :: OSI Approved :: MIT License
Classifier: Operating System :: OS Independent
